{
    "version": "1.188.4",
    "description": "An open-source Firebase alternative.",
    "homepage": "https://supabase.com/",
    "license": "MIT",
    "architecture": {
        "64bit": {
            "url": "https://github.com/supabase/cli/releases/download/v1.188.4/supabase_windows_amd64.tar.gz",
            "hash": "a5d90df623f3b094fcfe6e89f498a998f33233dfbf336735751dccd97f649fc3"
        }
    },
    "bin": "supabase.exe",
    "checkver": {
        "github": "https://github.com/supabase/cli"
    },
    "autoupdate": {
        "architecture": {
            "64bit": {
                "url": "https://github.com/supabase/cli/releases/download/v$version/supabase_windows_amd64.tar.gz"
            }
        },
        "hash": {
            "url": "$baseurl/supabase_$version_checksums.txt"
        }
    }
}
